ai_pose_generator_3/__init__.py
ai_pose_generator_3-1766999.123.877.dist-info/licenses/LICENSE
ai_pose_generator_3-1766999.123.877.dist-info/METADATA
ai_pose_generator_3-1766999.123.877.dist-info/WHEEL
ai_pose_generator_3-1766999.123.877.dist-info/top_level.txt
ai_pose_generator_3-1766999.123.877.dist-info/RECORD
