Metadata-Version: 2.4
Name: ai-pose-generator-3
Version: 1766999.123.877
Summary: High-quality integration for https://supermaker.ai/image/ai-pose-generator/
Home-page: https://supermaker.ai/image/ai-pose-generator/
Author: SuperMaker
Classifier: Programming Language :: Python :: 3
Classifier: License :: OSI Approved :: MIT License
Requires-Python: >=3.6
License-File: LICENSE
Dynamic: author
Dynamic: classifier
Dynamic: description
Dynamic: description-content-type
Dynamic: home-page
Dynamic: license-file
Dynamic: requires-python
Dynamic: summary
